{
  "capture_id": "20260315T031513-6ac187",
  "timestamp": "2026-03-15T03:15:13.781148Z",
  "adcs": {
    "timestamp": 1773544513.781148,
    "position_mcmf": [
      0.0,
      0.0,
      0.0
    ],
    "velocity_mps": [
      0.0,
      0.0,
      0.0
    ],
    "attitude_quaternion": [
      1.0,
      0.0,
      0.0,
      0.0
    ]
  },
  "regions": [
    {
      "bbox": [
        464,
        1038,
        22,
        28
      ],
      "area": 179.0
    },
    {
      "bbox": [
        1141,
        1031,
        17,
        33
      ],
      "area": 136.5
    },
    {
      "bbox": [
        145,
        1015,
        23,
        50
      ],
      "area": 134.5
    },
    {
      "bbox": [
        440,
        984,
        21,
        52
      ],
      "area": 205.5
    },
    {
      "bbox": [
        0,
        982,
        39,
        85
      ],
      "area": 274.5
    },
    {
      "bbox": [
        1136,
        960,
        13,
        66
      ],
      "area": 219.5
    },
    {
      "bbox": [
        152,
        952,
        271,
        40
      ],
      "area": 807.0
    },
    {
      "bbox": [
        852,
        947,
        22,
        9
      ],
      "area": 73.5
    },
    {
      "bbox": [
        141,
        930,
        290,
        45
      ],
      "area": 1065.5
    },
    {
      "bbox": [
        259,
        909,
        112,
        16
      ],
      "area": 121.5
    },
    {
      "bbox": [
        63,
        908,
        79,
        52
      ],
      "area": 206.5
    },
    {
      "bbox": [
        668,
        883,
        29,
        13
      ],
      "area": 62.5
    },
    {
      "bbox": [
        453,
        860,
        65,
        60
      ],
      "area": 425.5
    },
    {
      "bbox": [
        1161,
        854,
        29,
        160
      ],
      "area": 349.5
    },
    {
      "bbox": [
        436,
        818,
        45,
        80
      ],
      "area": 442.0
    },
    {
      "bbox": [
        1057,
        813,
        115,
        225
      ],
      "area": 1002.0
    },
    {
      "bbox": [
        436,
        740,
        22,
        28
      ],
      "area": 187.0
    },
    {
      "bbox": [
        1229,
        453,
        43,
        8
      ],
      "area": 54.5
    },
    {
      "bbox": [
        1124,
        397,
        8,
        48
      ],
      "area": 105.5
    },
    {
      "bbox": [
        1267,
        392,
        11,
        54
      ],
      "area": 130.0
    },
    {
      "bbox": [
        1145,
        392,
        7,
        76
      ],
      "area": 125.5
    },
    {
      "bbox": [
        1135,
        392,
        9,
        77
      ],
      "area": 126.5
    },
    {
      "bbox": [
        1154,
        391,
        7,
        75
      ],
      "area": 124.5
    },
    {
      "bbox": [
        1185,
        389,
        17,
        67
      ],
      "area": 427.5
    },
    {
      "bbox": [
        1172,
        388,
        7,
        75
      ],
      "area": 108.5
    },
    {
      "bbox": [
        1162,
        388,
        8,
        76
      ],
      "area": 132.5
    },
    {
      "bbox": [
        1282,
        380,
        5,
        64
      ],
      "area": 183.0
    },
    {
      "bbox": [
        1341,
        379,
        6,
        58
      ],
      "area": 84.0
    },
    {
      "bbox": [
        1197,
        371,
        70,
        12
      ],
      "area": 169.0
    },
    {
      "bbox": [
        1267,
        166,
        10,
        120
      ],
      "area": 425.0
    },
    {
      "bbox": [
        1302,
        152,
        28,
        100
      ],
      "area": 297.5
    }
  ],
  "matrix_shape": [
    36,
    64
  ],
  "matrix_data": [
    [
      0.0476190485060215,
      0.0,
      0.0,
      0.01587301678955555,
      0.0317460335791111,
      0.0,
      0.0,
      0.0,
      0.0476190485060215,
      0.0,
      0.0317460335791111,
      0.0,
      0.1111111119389534,
      0.0,
      0.01587301678955555,
      0.0,
      0.01587301678955555,
      0.01587301678955555,
      0.01587301678955555,
      0.01587301678955555,
      0.0634920671582222,
      0.0317460335791111,
      0.0317460335791111,
      0.01587301678955555,
      0.0317460335791111,
      0.0476190485060215,
      0.0,
      0.0,
      0.0,
      0.0,
      0.0,
      0.01587301678955555,
      0.0,
      0.01587301678955555,
      0.01587301678955555,
      0.0793650820851326,
      0.0,
      0.01587301678955555,
      0.01587301678955555,
      0.0,
      0.0,
      0.0,
      0.1428571492433548,
      0.0317460335791111,
      0.095238097012043,
      0.0317460335791111,
      0.0317460335791111,
      0.0,
      0.0,
      0.0,
      0.0,
      0.0317460335791111,
      0.0,
      0.01587301678955555,
      0.0476190485060215,
      0.095238097012043,
      0.0476190485060215,
      0.01587301678955555,
      0.0,
      0.01587301678955555,
      0.01587301678955555,
      0.0476190485060215,
      0.0317460335791111,
      0.1269841343164444
    ],
    [
      0.0,
      0.0634920671582222,
      0.0,
      0.0317460335791111,
      0.1111111119389534,
      0.1269841343164444,
      0.0317460335791111,
      0.01587301678955555,
      0.1111111119389534,
      0.0,
      0.1269841343164444,
      0.01587301678955555,
      0.01587301678955555,
      0.01587301678955555,
      0.01587301678955555,
      0.0793650820851326,
      0.0317460335791111,
      0.0317460335791111,
      0.0,
      0.01587301678955555,
      0.0,
      0.01587301678955555,
      0.01587301678955555,
      0.01587301678955555,
      0.0634920671582222,
      0.0,
      0.0317460335791111,
      0.0,
      0.01587301678955555,
      0.01587301678955555,
      0.0317460335791111,
      0.0317460335791111,
      0.0476190485060215,
      0.0793650820851326,
      0.0,
      0.0,
      0.0476190485060215,
      0.0476190485060215,
      0.0,
      0.0,
      0.01587301678955555,
      0.0,
      0.0,
      0.0,
      0.0,
      0.0,
      0.0476190485060215,
      0.01587301678955555,
      0.0,
      0.0,
      0.01587301678955555,
      0.0317460335791111,
      0.0,
      0.0,
      0.0,
      0.01587301678955555,
      0.0,
      0.0793650820851326,
      0.0,
      0.0476190485060215,
      0.0634920671582222,
      0.0317460335791111,
      0.0476190485060215,
      0.0
    ],
    [
      0.095238097012043,
      0.0317460335791111,
      0.0,
      0.0,
      0.095238097012043,
      0.0,
      0.0,
      0.095238097012043,
      0.0634920671582222,
      0.0476190485060215,
      0.2063492089509964,
      0.1111111119389534,
      0.01587301678955555,
      0.1587301641702652,
      0.0,
      0.0476190485060215,
      0.0,
      0.0,
      0.1111111119389534,
      0.01587301678955555,
      0.0317460335791111,
      0.0317460335791111,
      0.0,
      0.0317460335791111,
      0.0317460335791111,
      0.0317460335791111,
      0.0634920671582222,
      0.0476190485060215,
      0.0476190485060215,
      0.0317460335791111,
      0.0,
      0.01587301678955555,
      0.0476190485060215,
      0.0634920671582222,
      0.01587301678955555,
      0.0,
      0.01587301678955555,
      0.0,
      0.0,
      0.01587301678955555,
      0.0,
      0.0,
      0.0634920671582222,
      0.0,
      0.0,
      0.0,
      0.0793650820851326,
      0.0,
      0.01587301678955555,
      0.0,
      0.0634920671582222,
      0.0476190485060215,
      0.01587301678955555,
      0.01587301678955555,
      0.0,
      0.0,
      0.0317460335791111,
      0.0793650820851326,
      0.0476190485060215,
      0.0,
      0.0,
      0.0,
      0.0,
      0.0793650820851326
    ],
    [
      0.01587301678955555,
      0.01587301678955555,
      0.01587301678955555,
      0.0,
      0.0,
      0.0634920671582222,
      0.0793650820851326,
      0.0793650820851326,
      0.0793650820851326,
      0.01587301678955555,
      0.095238097012043,
      0.0,
      0.0,
      0.0317460335791111,
      0.0,
      0.0,
      0.0317460335791111,
      0.0,
      0.01587301678955555,
      0.0317460335791111,
      0.0317460335791111,
      0.01587301678955555,
      0.0317460335791111,
      0.0476190485060215,
      0.0476190485060215,
      0.0317460335791111,
      0.0,
      0.01587301678955555,
      0.0317460335791111,
      0.01587301678955555,
      0.0317460335791111,
      0.01587301678955555,
      0.0317460335791111,
      0.0,
      0.0,
      0.01587301678955555,
      0.0,
      0.0,
      0.0476190485060215,
      0.0,
      0.0,
      0.0,
      0.0476190485060215,
      0.0,
      0.0,
      0.0,
      0.0317460335791111,
      0.01587301678955555,
      0.0,
      0.0317460335791111,
      0.01587301678955555,
      0.0,
      0.0,
      0.01587301678955555,
      0.01587301678955555,
      0.0,
      0.01587301678955555,
      0.0634920671582222,
      0.0,
      0.0476190485060215,
      0.1111111119389534,
      0.190476194024086,
      0.0,
      0.01587301678955555
    ],
    [
      0.0317460335791111,
      0.0,
      0.0317460335791111,
      0.0476190485060215,
      0.0317460335791111,
      0.0,
      0.0476190485060215,
      0.01587301678955555,
      0.1587301641702652,
      0.0,
      0.0,
      0.0317460335791111,
      0.0,
      0.0476190485060215,
      0.01587301678955555,
      0.0634920671582222,
      0.01587301678955555,
      0.01587301678955555,
      0.0,
      0.095238097012043,
      0.0,
      0.0634920671582222,
      0.01587301678955555,
      0.0476190485060215,
      0.01587301678955555,
      0.0634920671582222,
      0.0793650820851326,
      0.0,
      0.0,
      0.0,
      0.0317460335791111,
      0.01587301678955555,
      0.0,
      0.01587301678955555,
      0.0,
      0.0317460335791111,
      0.01587301678955555,
      0.0634920671582222,
      0.0,
      0.0317460335791111,
      0.01587301678955555,
      0.0,
      0.0317460335791111,
      0.0317460335791111,
      0.0634920671582222,
      0.01587301678955555,
      0.0,
      0.01587301678955555,
      0.0476190485060215,
      0.0,
      0.0317460335791111,
      0.0,
      0.0634920671582222,
      0.0634920671582222,
      0.0,
      0.0,
      0.01587301678955555,
      0.0,
      0.01587301678955555,
      0.0,
      0.0,
      0.0,
      0.01587301678955555,
      0.1269841343164444
    ],
    [
      0.0793650820851326,
      0.0,
      0.01587301678955555,
      0.0,
      0.01587301678955555,
      0.095238097012043,
      0.0317460335791111,
      0.0317460335791111,
      0.0,
      0.0317460335791111,
      0.0793650820851326,
      0.0476190485060215,
      0.0634920671582222,
      0.0317460335791111,
      0.0317460335791111,
      0.0317460335791111,
      0.0476190485060215,
      0.01587301678955555,
      0.0476190485060215,
      0.0,
      0.01587301678955555,
      0.01587301678955555,
      0.0,
      0.01587301678955555,
      0.0,
      0.0,
      0.0,
      0.0317460335791111,
      0.0,
      0.01587301678955555,
      0.0634920671582222,
      0.01587301678955555,
      0.0,
      0.0,
      0.01587301678955555,
      0.0,
      0.0317460335791111,
      0.0317460335791111,
      0.0476190485060215,
      0.0,
      0.0,
      0.0,
      0.0793650820851326,
      0.3174603283405304,
      0.1111111119389534,
      0.01587301678955555,
      0.0,
      0.0,
      0.0634920671582222,
      0.0,
      0.0317460335791111,
      0.0317460335791111,
      0.0317460335791111,
      0.0,
      0.0476190485060215,
      0.0,
      0.0,
      0.0317460335791111,
      0.0317460335791111,
      0.0,
      0.0793650820851326,
      0.0476190485060215,
      0.01587301678955555,
      0.0793650820851326
    ],
    [
      0.01587301678955555,
      0.0,
      0.01587301678955555,
      0.0,
      0.01587301678955555,
      0.0,
      0.0317460335791111,
      0.01587301678955555,
      0.0,
      0.0317460335791111,
      0.095238097012043,
      0.0476190485060215,
      0.0317460335791111,
      0.0317460335791111,
      0.0476190485060215,
      0.0,
      0.01587301678955555,
      0.0634920671582222,
      0.0,
      0.0793650820851326,
      0.0317460335791111,
      0.0,
      0.0634920671582222,
      0.0,
      0.01587301678955555,
      0.0476190485060215,
      0.01587301678955555,
      0.0,
      0.0,
      0.01587301678955555,
      0.01587301678955555,
      0.0476190485060215,
      0.0317460335791111,
      0.01587301678955555,
      0.01587301678955555,
      0.0,
      0.01587301678955555,
      0.01587301678955555,
      0.0476190485060215,
      0.01587301678955555,
      0.0,
      0.0,
      0.4761904776096344,
      0.0,
      0.0,
      0.0317460335791111,
      0.0476190485060215,
      0.0,
      0.0,
      0.0,
      0.0,
      0.01587301678955555,
      0.1587301641702652,
      0.0,
      0.0,
      0.01587301678955555,
      0.01587301678955555,
      0.0317460335791111,
      0.01587301678955555,
      0.01587301678955555,
      0.0317460335791111,
      0.01587301678955555,
      0.01587301678955555,
      0.0476190485060215
    ],
    [
      0.01587301678955555,
      0.0317460335791111,
      0.01587301678955555,
      0.0634920671582222,
      0.0317460335791111,
      0.0,
      0.01587301678955555,
      0.0317460335791111,
      0.01587301678955555,
      0.0317460335791111,
      0.0634920671582222,
      0.2380952388048172,
      0.0,
      0.095238097012043,
      0.0,
      0.0317460335791111,
      0.0793650820851326,
      0.0476190485060215,
      0.0317460335791111,
      0.0,
      0.0317460335791111,
      0.0317460335791111,
      0.0476190485060215,
      0.0634920671582222,
      0.01587301678955555,
      0.0317460335791111,
      0.0,
      0.0317460335791111,
      0.01587301678955555,
      0.0,
      0.01587301678955555,
      0.01587301678955555,
      0.0476190485060215,
      0.0,
      0.0,
      0.0317460335791111,
      0.0,
      0.01587301678955555,
      0.0,
      0.0,
      0.01587301678955555,
      0.0317460335791111,
      0.3333333432674408,
      0.0,
      0.0317460335791111,
      0.01587301678955555,
      0.0,
      0.0,
      0.01587301678955555,
      0.0,
      0.0,
      0.01587301678955555,
      0.01587301678955555,
      0.0,
      0.1269841343164444,
      0.0476190485060215,
      0.0476190485060215,
      0.01587301678955555,
      0.0,
      0.0476190485060215,
      0.0476190485060215,
      0.1269841343164444,
      0.01587301678955555,
      0.0
    ],
    [
      0.095238097012043,
      0.0476190485060215,
      0.0,
      0.0,
      0.1428571492433548,
      0.0793650820851326,
      0.0,
      0.0,
      0.0476190485060215,
      0.0317460335791111,
      0.0317460335791111,
      0.0317460335791111,
      0.0476190485060215,
      0.0,
      0.01587301678955555,
      0.01587301678955555,
      0.0317460335791111,
      0.0317460335791111,
      0.0,
      0.01587301678955555,
      0.0317460335791111,
      0.0,
      0.0,
      0.01587301678955555,
      0.0,
      0.0,
      0.0793650820851326,
      0.0,
      0.0476190485060215,
      0.0476190485060215,
      0.0,
      0.0,
      0.0317460335791111,
      0.01587301678955555,
      0.01587301678955555,
      0.0,
      0.0,
      0.01587301678955555,
      0.0,
      0.01587301678955555,
      0.0,
      0.0317460335791111,
      0.3174603283405304,
      0.4126984179019928,
      0.0793650820851326,
      0.0,
      0.0317460335791111,
      0.0,
      0.01587301678955555,
      0.0,
      0.0793650820851326,
      0.0,
      0.01587301678955555,
      0.0,
      0.0,
      0.0,
      0.01587301678955555,
      0.0476190485060215,
      0.0,
      0.0317460335791111,
      0.0,
      0.0,
      0.0634920671582222,
      0.0
    ],
    [
      0.0,
      0.0317460335791111,
      0.1111111119389534,
      0.0,
      0.0476190485060215,
      0.0,
      0.0634920671582222,
      0.0,
      0.01587301678955555,
      0.0634920671582222,
      0.0476190485060215,
      0.01587301678955555,
      0.0,
      0.0,
      0.0,
      0.0,
      0.0317460335791111,
      0.01587301678955555,
      0.0,
      0.0634920671582222,
      0.0,
      0.0,
      0.0,
      0.0634920671582222,
      0.0317460335791111,
      0.01587301678955555,
      0.0317460335791111,
      0.0,
      0.0476190485060215,
      0.01587301678955555,
      0.0476190485060215,
      0.0,
      0.0,
      0.0317460335791111,
      0.01587301678955555,
      0.0,
      0.0,
      0.0317460335791111,
      0.01587301678955555,
      0.0317460335791111,
      0.0,
      0.0317460335791111,
      0.30158731341362,
      0.01587301678955555,
      0.01587301678955555,
      0.0,
      0.01587301678955555,
      0.0317460335791111,
      0.0,
      0.01587301678955555,
      0.0793650820851326,
      0.0,
      0.01587301678955555,
      0.01587301678955555,
      0.01587301678955555,
      0.0,
      0.01587301678955555,
      0.0,
      0.0,
      0.0,
      0.0317460335791111,
      0.01587301678955555,
      0.095238097012043,
      0.0634920671582222
    ],
    [
      0.1111111119389534,
      0.0,
      0.0317460335791111,
      0.0,
      0.0476190485060215,
      0.0793650820851326,
      0.0317460335791111,
      0.0793650820851326,
      0.0634920671582222,
      0.0317460335791111,
      0.01587301678955555,
      0.01587301678955555,
      0.01587301678955555,
      0.1111111119389534,
      0.0,
      0.0,
      0.0,
      0.0,
      0.095238097012043,
      0.0,
      0.0,
      0.01587301678955555,
      0.01587301678955555,
      0.01587301678955555,
      0.0476190485060215,
      0.0,
      0.0,
      0.01587301678955555,
      0.0,
      0.0,
      0.01587301678955555,
      0.0,
      0.0793650820851326,
      0.0793650820851326,
      0.0476190485060215,
      0.0634920671582222,
      0.01587301678955555,
      0.0634920671582222,
      0.0,
      0.0317460335791111,
      0.0476190485060215,
      0.0,
      0.0476190485060215,
      0.01587301678955555,
      0.0,
      0.0317460335791111,
      0.0317460335791111,
      0.01587301678955555,
      0.0317460335791111,
      0.0317460335791111,
      0.0,
      0.01587301678955555,
      0.0317460335791111,
      0.0,
      0.0,
      0.0634920671582222,
      0.01587301678955555,
      0.0,
      0.0,
      0.0317460335791111,
      0.0,
      0.0634920671582222,
      0.0317460335791111,
      0.0
    ],
    [
      0.01587301678955555,
      0.0476190485060215,
      0.0,
      0.0317460335791111,
      0.0,
      0.1269841343164444,
      0.0317460335791111,
      0.1269841343164444,
      0.0,
      0.0,
      0.0,
      0.0476190485060215,
      0.0,
      0.0476190485060215,
      0.0,
      0.0476190485060215,
      0.095238097012043,
      0.0317460335791111,
      0.01587301678955555,
      0.0,
      0.0476190485060215,
      0.0,
      0.0476190485060215,
      0.01587301678955555,
      0.0317460335791111,
      0.01587301678955555,
      0.01587301678955555,
      0.0317460335791111,
      0.0476190485060215,
      0.0,
      0.01587301678955555,
      0.0793650820851326,
      0.01587301678955555,
      0.01587301678955555,
      0.0,
      0.0,
      0.0476190485060215,
      0.0793650820851326,
      0.0317460335791111,
      0.01587301678955555,
      0.0317460335791111,
      0.0793650820851326,
      0.1428571492433548,
      0.0,
      0.0,
      0.095238097012043,
      0.0,
      0.01587301678955555,
      0.0,
      0.0,
      0.095238097012043,
      0.0,
      0.0634920671582222,
      0.01587301678955555,
      0.0317460335791111,
      0.0,
      0.0476190485060215,
      0.01587301678955555,
      0.0,
      0.0,
      0.095238097012043,
      0.0634920671582222,
      0.0,
      0.0
    ],
    [
      0.01587301678955555,
      0.0,
      0.0,
      0.0,
      0.0634920671582222,
      0.01587301678955555,
      0.0317460335791111,
      0.1111111119389534,
      0.0793650820851326,
      0.0,
      0.0,
      0.0793650820851326,
      0.0317460335791111,
      0.0476190485060215,
      0.0,
      0.0476190485060215,
      0.0317460335791111,
      0.0,
      0.01587301678955555,
      0.0317460335791111,
      0.01587301678955555,
      0.0476190485060215,
      0.0,
      0.01587301678955555,
      0.01587301678955555,
      0.01587301678955555,
      0.0,
      0.01587301678955555,
      0.0,
      0.01587301678955555,
      0.0476190485060215,
      0.0476190485060215,
      0.0,
      0.0793650820851326,
      0.0,
      0.0,
      0.0476190485060215,
      0.0,
      0.0476190485060215,
      0.1269841343164444,
      0.1428571492433548,
      0.4444444477558136,
      0.1746031790971756,
      0.1269841343164444,
      0.190476194024086,
      0.095238097012043,
      0.0476190485060215,
      0.0317460335791111,
      0.0,
      0.0634920671582222,
      0.0476190485060215,
      0.1428571492433548,
      0.1269841343164444,
      0.0,
      0.0,
      0.01587301678955555,
      0.0476190485060215,
      0.0317460335791111,
      0.0,
      0.01587301678955555,
      0.0,
      0.0476190485060215,
      0.01587301678955555,
      0.0476190485060215
    ],
    [
      0.0634920671582222,
      0.0476190485060215,
      0.0,
      0.0317460335791111,
      0.01587301678955555,
      0.0,
      0.0476190485060215,
      0.01587301678955555,
      0.01587301678955555,
      0.1111111119389534,
      0.0,
      0.0,
      0.0634920671582222,
      0.0317460335791111,
      0.01587301678955555,
      0.01587301678955555,
      0.01587301678955555,
      0.01587301678955555,
      0.0,
      0.0317460335791111,
      0.0634920671582222,
      0.095238097012043,
      0.01587301678955555,
      0.0,
      0.01587301678955555,
      0.01587301678955555,
      0.01587301678955555,
      0.01587301678955555,
      0.0,
      0.0,
      0.0,
      0.0317460335791111,
      0.0,
      0.0,
      0.0317460335791111,
      0.0,
      0.01587301678955555,
      0.2063492089509964,
      0.0476190485060215,
      0.30158731341362,
      0.2539682686328888,
      0.0317460335791111,
      0.1111111119389534,
      0.30158731341362,
      0.0,
      0.0317460335791111,
      0.01587301678955555,
      0.0317460335791111,
      0.01587301678955555,
      0.01587301678955555,
      0.0317460335791111,
      0.01587301678955555,
      0.0634920671582222,
      0.0,
      0.0,
      0.01587301678955555,
      0.01587301678955555,
      0.0,
      0.0634920671582222,
      0.0,
      0.0317460335791111,
      0.0,
      0.1428571492433548,
      0.0634920671582222
    ],
    [
      0.01587301678955555,
      0.01587301678955555,
      0.01587301678955555,
      0.01587301678955555,
      0.0476190485060215,
      0.0,
      0.0476190485060215,
      0.0317460335791111,
      0.0,
      0.01587301678955555,
      0.01587301678955555,
      0.0,
      0.1111111119389534,
      0.01587301678955555,
      0.0,
      0.0,
      0.0634920671582222,
      0.0476190485060215,
      0.2063492089509964,
      0.01587301678955555,
      0.0,
      0.0,
      0.0793650820851326,
      0.0317460335791111,
      0.2222222238779068,
      0.095238097012043,
      0.0,
      0.0317460335791111,
      0.0476190485060215,
      0.0,
      0.01587301678955555,
      0.0634920671582222,
      0.01587301678955555,
      0.0317460335791111,
      0.0317460335791111,
      0.0317460335791111,
      0.01587301678955555,
      0.2222222238779068,
      0.0,
      0.1746031790971756,
      0.0476190485060215,
      0.0317460335791111,
      0.1587301641702652,
      0.2380952388048172,
      0.0,
      0.0,
      0.0476190485060215,
      0.0476190485060215,
      0.0317460335791111,
      0.01587301678955555,
      0.0,
      0.0,
      0.01587301678955555,
      0.0476190485060215,
      0.01587301678955555,
      0.0,
      0.0,
      0.01587301678955555,
      0.0793650820851326,
      0.0634920671582222,
      0.01587301678955555,
      0.0317460335791111,
      0.01587301678955555,
      0.190476194024086
    ],
    [
      0.0,
      0.095238097012043,
      0.0317460335791111,
      0.01587301678955555,
      0.01587301678955555,
      0.0317460335791111,
      0.0,
      0.0476190485060215,
      0.0634920671582222,
      0.0317460335791111,
      0.0317460335791111,
      0.0,
      0.0793650820851326,
      0.0317460335791111,
      0.0317460335791111,
      0.0,
      0.01587301678955555,
      0.095238097012043,
      0.0,
      0.0,
      0.01587301678955555,
      0.0,
      0.0,
      0.0,
      0.1746031790971756,
      0.0,
      0.190476194024086,
      0.0317460335791111,
      0.0317460335791111,
      0.0634920671582222,
      0.0634920671582222,
      0.01587301678955555,
      0.01587301678955555,
      0.0476190485060215,
      0.0476190485060215,
      0.0,
      0.0,
      0.1587301641702652,
      0.0317460335791111,
      0.1587301641702652,
      0.1587301641702652,
      0.0476190485060215,
      0.0634920671582222,
      0.0,
      0.0,
      0.01587301678955555,
      0.0793650820851326,
      0.01587301678955555,
      0.0,
      0.0,
      0.0317460335791111,
      0.0,
      0.0,
      0.0317460335791111,
      0.0476190485060215,
      0.0,
      0.01587301678955555,
      0.0317460335791111,
      0.01587301678955555,
      0.0,
      0.0634920671582222,
      0.0793650820851326,
      0.0476190485060215,
      0.01587301678955555
    ],
    [
      0.01587301678955555,
      0.095238097012043,
      0.01587301678955555,
      0.0317460335791111,
      0.01587301678955555,
      0.01587301678955555,
      0.1269841343164444,
      0.01587301678955555,
      0.0476190485060215,
      0.01587301678955555,
      0.01587301678955555,
      0.0,
      0.01587301678955555,
      0.0317460335791111,
      0.0,
      0.0,
      0.0,
      0.0,
      0.0634920671582222,
      0.0,
      0.0,
      0.0793650820851326,
      0.0476190485060215,
      0.0,
      0.1111111119389534,
      0.095238097012043,
      0.0317460335791111,
      0.0,
      0.0,
      0.0476190485060215,
      0.0,
      0.01587301678955555,
      0.0317460335791111,
      0.0,
      0.01587301678955555,
      0.01587301678955555,
      0.0317460335791111,
      0.0317460335791111,
      0.0,
      0.0,
      0.0476190485060215,
      0.01587301678955555,
      0.0317460335791111,
      0.0,
      0.0317460335791111,
      0.0634920671582222,
      0.01587301678955555,
      0.0317460335791111,
      0.01587301678955555,
      0.0634920671582222,
      0.0,
      0.0,
      0.0,
      0.0,
      0.0,
      0.0,
      0.0634920671582222,
      0.0,
      0.1428571492433548,
      0.0793650820851326,
      0.0,
      0.0,
      0.1111111119389534,
      0.01587301678955555
    ],
    [
      0.0634920671582222,
      0.0317460335791111,
      0.01587301678955555,
      0.1111111119389534,
      0.01587301678955555,
      0.0,
      0.0634920671582222,
      0.0476190485060215,
      0.0,
      0.0317460335791111,
      0.0317460335791111,
      0.0476190485060215,
      0.1111111119389534,
      0.0,
      0.0793650820851326,
      0.0,
      0.01587301678955555,
      0.0,
      0.0,
      0.095238097012043,
      0.0,
      0.0,
      0.0,
      0.01587301678955555,
      0.095238097012043,
      0.01587301678955555,
      0.0,
      0.190476194024086,
      0.0,
      0.0,
      0.0,
      0.1111111119389534,
      0.01587301678955555,
      0.01587301678955555,
      0.01587301678955555,
      0.0,
      0.0,
      0.0,
      0.01587301678955555,
      0.01587301678955555,
      0.01587301678955555,
      0.0476190485060215,
      0.01587301678955555,
      0.0,
      0.095238097012043,
      0.0634920671582222,
      0.01587301678955555,
      0.0,
      0.0634920671582222,
      0.01587301678955555,
      0.0,
      0.0476190485060215,
      0.0317460335791111,
      0.01587301678955555,
      0.095238097012043,
      0.0,
      0.1428571492433548,
      0.0317460335791111,
      0.0,
      0.0317460335791111,
      0.0317460335791111,
      0.0476190485060215,
      0.0634920671582222,
      0.0634920671582222
    ],
    [
      0.0317460335791111,
      0.0317460335791111,
      0.0,
      0.0793650820851326,
      0.0476190485060215,
      0.01587301678955555,
      0.0,
      0.0476190485060215,
      0.0,
      0.0,
      0.0,
      0.0476190485060215,
      0.0,
      0.0476190485060215,
      0.0,
      0.0793650820851326,
      0.0,
      0.0,
      0.095238097012043,
      0.1746031790971756,
      0.0,
      0.0,
      0.0,
      0.0,
      0.0,
      0.01587301678955555,
      0.0634920671582222,
      0.0,
      0.01587301678955555,
      0.0317460335791111,
      0.1111111119389534,
      0.0,
      0.0317460335791111,
      0.0317460335791111,
      0.0,
      0.01587301678955555,
      0.0,
      0.0,
      0.01587301678955555,
      0.01587301678955555,
      0.0476190485060215,
      0.0476190485060215,
      0.0634920671582222,
      0.0,
      0.0,
      0.0,
      0.01587301678955555,
      0.0317460335791111,
      0.0,
      0.1269841343164444,
      0.01587301678955555,
      0.0,
      0.01587301678955555,
      0.0317460335791111,
      0.0317460335791111,
      0.0,
      0.0,
      0.0793650820851326,
      0.0,
      0.0,
      0.0476190485060215,
      0.1428571492433548,
      0.0476190485060215,
      0.0476190485060215
    ],
    [
      0.0,
      0.01587301678955555,
      0.0,
      0.01587301678955555,
      0.0317460335791111,
      0.0,
      0.0476190485060215,
      0.01587301678955555,
      0.0,
      0.0476190485060215,
      0.01587301678955555,
      0.0317460335791111,
      0.0317460335791111,
      0.095238097012043,
      0.0,
      0.0634920671582222,
      0.0,
      0.1269841343164444,
      0.0,
      0.0,
      0.0793650820851326,
      0.0476190485060215,
      0.0,
      0.0476190485060215,
      0.0,
      0.0,
      0.0,
      0.0476190485060215,
      0.0,
      0.0,
      0.0,
      0.01587301678955555,
      0.0,
      0.0317460335791111,
      0.01587301678955555,
      0.0476190485060215,
      0.01587301678955555,
      0.0317460335791111,
      0.0317460335791111,
      0.0,
      0.0317460335791111,
      0.0476190485060215,
      0.0,
      0.0634920671582222,
      0.0,
      0.0,
      0.0,
      0.1428571492433548,
      0.01587301678955555,
      0.095238097012043,
      0.1269841343164444,
      0.0,
      0.0,
      0.1746031790971756,
      0.01587301678955555,
      0.1111111119389534,
      0.1111111119389534,
      0.01587301678955555,
      0.0,
      0.0793650820851326,
      0.0793650820851326,
      0.01587301678955555,
      0.0,
      0.0634920671582222
    ],
    [
      0.0634920671582222,
      0.0,
      0.0,
      0.0,
      0.0317460335791111,
      0.01587301678955555,
      0.1111111119389534,
      0.01587301678955555,
      0.0,
      0.0,
      0.01587301678955555,
      0.0476190485060215,
      0.0634920671582222,
      0.0,
      0.0,
      0.0634920671582222,
      0.0793650820851326,
      0.0,
      0.01587301678955555,
      0.1269841343164444,
      0.0,
      0.0,
      0.0,
      0.01587301678955555,
      0.01587301678955555,
      0.0,
      0.0317460335791111,
      0.0,
      0.0317460335791111,
      0.0,
      0.01587301678955555,
      0.01587301678955555,
      0.0793650820851326,
      0.0,
      0.0634920671582222,
      0.0,
      0.01587301678955555,
      0.0476190485060215,
      0.0476190485060215,
      0.01587301678955555,
      0.0,
      0.095238097012043,
      0.1428571492433548,
      0.095238097012043,
      0.0476190485060215,
      0.0,
      0.01587301678955555,
      0.01587301678955555,
      0.1587301641702652,
      0.1587301641702652,
      0.1111111119389534,
      0.0,
      0.0476190485060215,
      0.0,
      0.01587301678955555,
      0.0,
      0.0,
      0.1587301641702652,
      0.095238097012043,
      0.0,
      0.0,
      0.0317460335791111,
      0.0634920671582222,
      0.0793650820851326
    ],
    [
      0.0634920671582222,
      0.1587301641702652,
      0.0476190485060215,
      0.0634920671582222,
      0.0,
      0.01587301678955555,
      0.0317460335791111,
      0.0,
      0.0,
      0.1587301641702652,
      0.0476190485060215,
      0.0317460335791111,
      0.0,
      0.0793650820851326,
      0.01587301678955555,
      0.0634920671582222,
      0.0,
      0.095238097012043,
      0.01587301678955555,
      0.0,
      0.0,
      0.0634920671582222,
      0.0634920671582222,
      0.0476190485060215,
      0.0,
      0.0476190485060215,
      0.0476190485060215,
      0.095238097012043,
      0.0,
      0.0,
      0.0,
      0.0793650820851326,
      0.0,
      0.0,
      0.1111111119389534,
      0.0476190485060215,
      0.1111111119389534,
      0.0634920671582222,
      0.0,
      0.0,
      0.01587301678955555,
      0.190476194024086,
      0.0634920671582222,
      0.0634920671582222,
      0.0,
      0.0,
      0.01587301678955555,
      0.0793650820851326,
      0.0,
      0.0793650820851326,
      0.0317460335791111,
      0.0634920671582222,
      0.0,
      0.01587301678955555,
      0.0,
      0.0,
      0.0,
      0.0476190485060215,
      0.0317460335791111,
      0.0317460335791111,
      0.01587301678955555,
      0.0,
      0.0634920671582222,
      0.0
    ],
    [
      0.0793650820851326,
      0.0476190485060215,
      0.01587301678955555,
      0.0,
      0.0317460335791111,
      0.0634920671582222,
      0.0,
      0.01587301678955555,
      0.01587301678955555,
      0.0,
      0.0,
      0.0,
      0.0634920671582222,
      0.0317460335791111,
      0.0317460335791111,
      0.0,
      0.0,
      0.0,
      0.0793650820851326,
      0.0793650820851326,
      0.0476190485060215,
      0.0317460335791111,
      0.0317460335791111,
      0.01587301678955555,
      0.0,
      0.0,
      0.0634920671582222,
      0.01587301678955555,
      0.0793650820851326,
      0.0,
      0.0317460335791111,
      0.01587301678955555,
      0.0,
      0.0793650820851326,
      0.0,
      0.0317460335791111,
      0.2698412835597992,
      0.0,
      0.0,
      0.095238097012043,
      0.0317460335791111,
      0.0476190485060215,
      0.0476190485060215,
      0.01587301678955555,
      0.0,
      0.0,
      0.01587301678955555,
      0.0,
      0.0317460335791111,
      0.01587301678955555,
      0.0,
      0.0,
      0.0,
      0.01587301678955555,
      0.01587301678955555,
      0.0,
      0.0317460335791111,
      0.01587301678955555,
      0.01587301678955555,
      0.0,
      0.0476190485060215,
      0.01587301678955555,
      0.01587301678955555,
      0.0
    ],
    [
      0.0,
      0.0,
      0.01587301678955555,
      0.0317460335791111,
      0.0317460335791111,
      0.0317460335791111,
      0.01587301678955555,
      0.0317460335791111,
      0.01587301678955555,
      0.0,
      0.0476190485060215,
      0.0,
      0.190476194024086,
      0.01587301678955555,
      0.0317460335791111,
      0.0317460335791111,
      0.1587301641702652,
      0.0793650820851326,
      0.0793650820851326,
      0.0634920671582222,
      0.0,
      0.0317460335791111,
      0.01587301678955555,
      0.01587301678955555,
      0.0,
      0.0476190485060215,
      0.0634920671582222,
      0.0317460335791111,
      0.0317460335791111,
      0.01587301678955555,
      0.01587301678955555,
      0.0,
      0.0,
      0.0,
      0.0,
      0.095238097012043,
      0.0634920671582222,
      0.01587301678955555,
      0.0,
      0.0317460335791111,
      0.01587301678955555,
      0.01587301678955555,
      0.01587301678955555,
      0.0317460335791111,
      0.0317460335791111,
      0.0,
      0.0317460335791111,
      0.0317460335791111,
      0.01587301678955555,
      0.0,
      0.0317460335791111,
      0.0317460335791111,
      0.0317460335791111,
      0.01587301678955555,
      0.0,
      0.0,
      0.0,
      0.0,
      0.0,
      0.0,
      0.0634920671582222,
      0.1111111119389534,
      0.01587301678955555,
      0.0
    ],
    [
      0.01587301678955555,
      0.0317460335791111,
      0.01587301678955555,
      0.0,
      0.0,
      0.0,
      0.01587301678955555,
      0.0,
      0.0634920671582222,
      0.0,
      0.0,
      0.0634920671582222,
      0.190476194024086,
      0.0,
      0.0,
      0.2539682686328888,
      0.0793650820851326,
      0.0634920671582222,
      0.01587301678955555,
      0.01587301678955555,
      0.0476190485060215,
      0.01587301678955555,
      0.0317460335791111,
      0.0476190485060215,
      0.0317460335791111,
      0.0,
      0.0,
      0.01587301678955555,
      0.0,
      0.0,
      0.1587301641702652,
      0.2698412835597992,
      0.2380952388048172,
      0.0,
      0.1111111119389534,
      0.01587301678955555,
      0.0317460335791111,
      0.01587301678955555,
      0.0,
      0.0634920671582222,
      0.0,
      0.0317460335791111,
      0.01587301678955555,
      0.0,
      0.0317460335791111,
      0.0317460335791111,
      0.01587301678955555,
      0.0,
      0.01587301678955555,
      0.01587301678955555,
      0.01587301678955555,
      0.01587301678955555,
      0.0476190485060215,
      0.01587301678955555,
      0.0317460335791111,
      0.0,
      0.0476190485060215,
      0.0,
      0.0,
      0.0317460335791111,
      0.0476190485060215,
      0.01587301678955555,
      0.095238097012043,
      0.0476190485060215
    ],
    [
      0.0634920671582222,
      0.0,
      0.0317460335791111,
      0.01587301678955555,
      0.0,
      0.095238097012043,
      0.01587301678955555,
      0.0,
      0.0634920671582222,
      0.0634920671582222,
      0.0634920671582222,
      0.0317460335791111,
      0.01587301678955555,
      0.0,
      0.0476190485060215,
      0.0,
      0.0,
      0.1111111119389534,
      0.0,
      0.0476190485060215,
      0.0317460335791111,
      0.0,
      0.1428571492433548,
      0.01587301678955555,
      0.01587301678955555,
      0.0476190485060215,
      0.0317460335791111,
      0.1269841343164444,
      0.0476190485060215,
      0.0,
      0.0634920671582222,
      0.01587301678955555,
      0.0,
      0.0,
      0.01587301678955555,
      0.2063492089509964,
      0.0634920671582222,
      0.0,
      0.0,
      0.0317460335791111,
      0.0,
      0.0,
      0.0476190485060215,
      0.0,
      0.0,
      0.0476190485060215,
      0.0,
      0.0317460335791111,
      0.0476190485060215,
      0.0,
      0.0,
      0.0,
      0.0,
      0.0,
      0.01587301678955555,
      0.0,
      0.01587301678955555,
      0.0317460335791111,
      0.0317460335791111,
      0.0,
      0.0317460335791111,
      0.0476190485060215,
      0.01587301678955555,
      0.01587301678955555
    ],
    [
      0.0317460335791111,
      0.01587301678955555,
      0.0,
      0.0317460335791111,
      0.1428571492433548,
      0.0,
      0.0,
      0.0,
      0.0,
      0.0476190485060215,
      0.0793650820851326,
      0.01587301678955555,
      0.0,
      0.0634920671582222,
      0.0,
      0.01587301678955555,
      0.01587301678955555,
      0.0317460335791111,
      0.0793650820851326,
      0.0,
      0.01587301678955555,
      0.0,
      0.0317460335791111,
      0.0,
      0.0634920671582222,
      0.01587301678955555,
      0.0476190485060215,
      0.0317460335791111,
      0.01587301678955555,
      0.0,
      0.0793650820851326,
      0.0,
      0.0317460335791111,
      0.0,
      0.0,
      0.190476194024086,
      0.01587301678955555,
      0.0476190485060215,
      0.0317460335791111,
      0.0,
      0.0317460335791111,
      0.0,
      0.0,
      0.01587301678955555,
      0.0,
      0.0,
      0.01587301678955555,
      0.01587301678955555,
      0.0,
      0.01587301678955555,
      0.0476190485060215,
      0.0317460335791111,
      0.01587301678955555,
      0.0,
      0.0,
      0.0476190485060215,
      0.0,
      0.0317460335791111,
      0.0,
      0.0,
      0.0,
      0.0,
      0.0,
      0.01587301678955555
    ],
    [
      0.0317460335791111,
      0.0317460335791111,
      0.0317460335791111,
      0.1111111119389534,
      0.0793650820851326,
      0.0,
      0.01587301678955555,
      0.0476190485060215,
      0.0,
      0.095238097012043,
      0.0317460335791111,
      0.0476190485060215,
      0.0,
      0.0793650820851326,
      0.0,
      0.0634920671582222,
      0.0,
      0.01587301678955555,
      0.0,
      0.0476190485060215,
      0.01587301678955555,
      0.0,
      0.0,
      0.01587301678955555,
      0.0,
      0.0317460335791111,
      0.01587301678955555,
      0.0476190485060215,
      0.01587301678955555,
      0.01587301678955555,
      0.0317460335791111,
      0.0,
      0.095238097012043,
      0.0317460335791111,
      0.01587301678955555,
      0.3333333432674408,
      0.0,
      0.0793650820851326,
      0.190476194024086,
      0.0,
      0.0,
      0.0317460335791111,
      0.01587301678955555,
      0.0317460335791111,
      0.0,
      0.0,
      0.0,
      0.01587301678955555,
      0.01587301678955555,
      0.01587301678955555,
      0.0793650820851326,
      0.01587301678955555,
      0.0,
      0.0,
      0.0,
      0.0476190485060215,
      0.0,
      0.0,
      0.01587301678955555,
      0.0,
      0.0317460335791111,
      0.01587301678955555,
      0.0476190485060215,
      0.0317460335791111
    ],
    [
      0.0476190485060215,
      0.0476190485060215,
      0.0476190485060215,
      0.0,
      0.01587301678955555,
      0.01587301678955555,
      0.01587301678955555,
      0.095238097012043,
      0.0317460335791111,
      0.0,
      0.0,
      0.0634920671582222,
      0.01587301678955555,
      0.0476190485060215,
      0.0,
      0.0,
      0.0,
      0.01587301678955555,
      0.0634920671582222,
      0.01587301678955555,
      0.0317460335791111,
      0.0,
      0.0476190485060215,
      0.0634920671582222,
      0.0476190485060215,
      0.0,
      0.0,
      0.0317460335791111,
      0.01587301678955555,
      0.0,
      0.01587301678955555,
      0.0,
      0.01587301678955555,
      0.0,
      0.0,
      0.1111111119389534,
      0.01587301678955555,
      0.0,
      0.0,
      0.0476190485060215,
      0.0,
      0.01587301678955555,
      0.0,
      0.01587301678955555,
      0.01587301678955555,
      0.01587301678955555,
      0.0,
      0.01587301678955555,
      0.0,
      0.0,
      0.01587301678955555,
      0.0,
      0.01587301678955555,
      0.0,
      0.0634920671582222,
      0.0476190485060215,
      0.01587301678955555,
      0.01587301678955555,
      0.0476190485060215,
      0.0634920671582222,
      0.01587301678955555,
      0.0317460335791111,
      0.0,
      0.0317460335791111
    ],
    [
      0.0,
      0.1428571492433548,
      0.0,
      0.0634920671582222,
      0.0476190485060215,
      0.01587301678955555,
      0.0,
      0.01587301678955555,
      0.01587301678955555,
      0.0476190485060215,
      0.0,
      0.0793650820851326,
      0.0,
      0.0317460335791111,
      0.1269841343164444,
      0.0,
      0.0,
      0.0,
      0.0,
      0.0,
      0.01587301678955555,
      0.01587301678955555,
      0.0,
      0.30158731341362,
      0.0,
      0.0,
      0.095238097012043,
      0.2380952388048172,
      0.0634920671582222,
      0.0,
      0.01587301678955555,
      0.01587301678955555,
      0.0317460335791111,
      0.0476190485060215,
      0.01587301678955555,
      0.0317460335791111,
      0.01587301678955555,
      0.2063492089509964,
      0.0,
      0.0793650820851326,
      0.0,
      0.0317460335791111,
      0.0,
      0.0,
      0.0,
      0.01587301678955555,
      0.0317460335791111,
      0.0,
      0.0476190485060215,
      0.01587301678955555,
      0.0,
      0.0476190485060215,
      0.0317460335791111,
      0.0,
      0.0,
      0.0634920671582222,
      0.0317460335791111,
      0.0,
      0.0317460335791111,
      0.0,
      0.01587301678955555,
      0.0,
      0.0317460335791111,
      0.0
    ],
    [
      0.0793650820851326,
      0.0,
      0.380952388048172,
      0.01587301678955555,
      0.0317460335791111,
      0.01587301678955555,
      0.01587301678955555,
      0.095238097012043,
      0.2063492089509964,
      0.0,
      0.0793650820851326,
      0.1111111119389534,
      0.0,
      0.0476190485060215,
      0.1111111119389534,
      0.0,
      0.0,
      0.0,
      0.01587301678955555,
      0.01587301678955555,
      0.0317460335791111,
      0.0634920671582222,
      0.0,
      0.0476190485060215,
      0.0793650820851326,
      0.0,
      0.0476190485060215,
      0.01587301678955555,
      0.01587301678955555,
      0.0634920671582222,
      0.01587301678955555,
      0.01587301678955555,
      0.0476190485060215,
      0.0,
      0.0317460335791111,
      0.190476194024086,
      0.0,
      0.0793650820851326,
      0.0793650820851326,
      0.190476194024086,
      0.01587301678955555,
      0.0317460335791111,
      0.0317460335791111,
      0.0,
      0.0,
      0.01587301678955555,
      0.0,
      0.0,
      0.0,
      0.0,
      0.01587301678955555,
      0.01587301678955555,
      0.0317460335791111,
      0.0317460335791111,
      0.01587301678955555,
      0.0,
      0.0,
      0.0317460335791111,
      0.01587301678955555,
      0.01587301678955555,
      0.0,
      0.0,
      0.0476190485060215,
      0.0317460335791111
    ],
    [
      0.01587301678955555,
      0.0793650820851326,
      0.01587301678955555,
      0.0,
      0.0634920671582222,
      0.0,
      0.0,
      0.2857142984867096,
      0.0317460335791111,
      0.2222222238779068,
      0.0,
      1.0,
      0.0,
      0.0,
      0.0793650820851326,
      0.0317460335791111,
      0.0,
      0.1428571492433548,
      0.0634920671582222,
      0.0317460335791111,
      0.0,
      0.0476190485060215,
      0.0,
      0.0476190485060215,
      0.01587301678955555,
      0.0793650820851326,
      0.0,
      0.1428571492433548,
      0.2222222238779068,
      0.0,
      0.1111111119389534,
      0.0,
      0.01587301678955555,
      0.01587301678955555,
      0.0,
      0.0793650820851326,
      0.01587301678955555,
      0.01587301678955555,
      0.5079365372657776,
      0.0,
      0.0,
      0.0,
      0.01587301678955555,
      0.01587301678955555,
      0.01587301678955555,
      0.0317460335791111,
      0.0317460335791111,
      0.0,
      0.01587301678955555,
      0.0317460335791111,
      0.01587301678955555,
      0.0,
      0.0,
      0.0317460335791111,
      0.01587301678955555,
      0.01587301678955555,
      0.0317460335791111,
      0.01587301678955555,
      0.0,
      0.01587301678955555,
      0.0,
      0.0793650820851326,
      0.0,
      0.0317460335791111
    ],
    [
      0.0,
      0.0,
      0.0,
      0.0,
      0.0634920671582222,
      0.0,
      0.0,
      0.0,
      0.3492063581943512,
      0.3174603283405304,
      0.0,
      0.0,
      0.0,
      0.0,
      0.0634920671582222,
      0.0,
      0.1428571492433548,
      0.0634920671582222,
      0.01587301678955555,
      0.0793650820851326,
      0.0476190485060215,
      0.0,
      0.0,
      0.0,
      0.1111111119389534,
      0.0,
      0.0,
      0.0,
      0.0793650820851326,
      0.0,
      0.2222222238779068,
      0.0,
      0.0317460335791111,
      0.1111111119389534,
      0.0,
      0.0793650820851326,
      0.0317460335791111,
      0.095238097012043,
      0.0,
      0.01587301678955555,
      0.01587301678955555,
      0.0,
      0.0,
      0.0,
      0.0,
      0.01587301678955555,
      0.0,
      0.0634920671582222,
      0.01587301678955555,
      0.0,
      0.01587301678955555,
      0.0,
      0.0,
      0.01587301678955555,
      0.0,
      0.01587301678955555,
      0.0,
      0.01587301678955555,
      0.01587301678955555,
      0.0793650820851326,
      0.01587301678955555,
      0.0634920671582222,
      0.0,
      0.0476190485060215
    ],
    [
      0.0317460335791111,
      0.0,
      0.095238097012043,
      0.01587301678955555,
      0.01587301678955555,
      0.0,
      0.0,
      0.0,
      0.1111111119389534,
      0.0317460335791111,
      0.01587301678955555,
      0.0317460335791111,
      0.0,
      0.0317460335791111,
      0.0,
      0.0317460335791111,
      0.0,
      0.01587301678955555,
      0.0634920671582222,
      0.0,
      0.095238097012043,
      0.01587301678955555,
      0.01587301678955555,
      0.0476190485060215,
      0.01587301678955555,
      0.0,
      0.0793650820851326,
      0.0,
      0.0,
      0.01587301678955555,
      0.01587301678955555,
      0.0,
      0.0,
      0.0634920671582222,
      0.0,
      0.0,
      0.0634920671582222,
      0.095238097012043,
      0.0,
      0.3333333432674408,
      0.01587301678955555,
      0.01587301678955555,
      0.0,
      0.0,
      0.0317460335791111,
      0.0,
      0.0,
      0.01587301678955555,
      0.01587301678955555,
      0.01587301678955555,
      0.0476190485060215,
      0.0,
      0.01587301678955555,
      0.01587301678955555,
      0.0317460335791111,
      0.0634920671582222,
      0.01587301678955555,
      0.01587301678955555,
      0.01587301678955555,
      0.0,
      0.0476190485060215,
      0.0,
      0.01587301678955555,
      0.0317460335791111
    ],
    [
      0.01587301678955555,
      0.1111111119389534,
      0.01587301678955555,
      0.0,
      0.0,
      0.0,
      0.0,
      0.0,
      0.01587301678955555,
      0.01587301678955555,
      0.0634920671582222,
      0.0317460335791111,
      0.0317460335791111,
      0.0,
      0.01587301678955555,
      0.190476194024086,
      0.0317460335791111,
      0.0,
      0.0476190485060215,
      0.0,
      0.0476190485060215,
      0.0317460335791111,
      0.0,
      0.0476190485060215,
      0.01587301678955555,
      0.0476190485060215,
      0.01587301678955555,
      0.01587301678955555,
      0.01587301678955555,
      0.0,
      0.0,
      0.2063492089509964,
      0.0476190485060215,
      0.0,
      0.0476190485060215,
      0.3333333432674408,
      0.0793650820851326,
      0.0476190485060215,
      0.2222222238779068,
      0.0,
      0.0,
      0.0,
      0.0,
      0.0,
      0.0,
      0.0317460335791111,
      0.01587301678955555,
      0.0,
      0.0,
      0.01587301678955555,
      0.01587301678955555,
      0.0317460335791111,
      0.0,
      0.0,
      0.0,
      0.0317460335791111,
      0.0476190485060215,
      0.0,
      0.0,
      0.01587301678955555,
      0.0,
      0.0,
      0.0,
      0.0
    ],
    [
      0.0317460335791111,
      0.0317460335791111,
      0.0634920671582222,
      0.0476190485060215,
      0.0476190485060215,
      0.0,
      0.0317460335791111,
      0.0476190485060215,
      0.0,
      0.01587301678955555,
      0.0,
      0.0793650820851326,
      0.01587301678955555,
      0.01587301678955555,
      0.01587301678955555,
      0.01587301678955555,
      0.0,
      0.0634920671582222,
      0.0476190485060215,
      0.2857142984867096,
      0.0476190485060215,
      0.0,
      0.01587301678955555,
      0.01587301678955555,
      0.01587301678955555,
      0.0317460335791111,
      0.01587301678955555,
      0.1428571492433548,
      0.0,
      0.0,
      0.0,
      0.0,
      0.0,
      0.0,
      0.0,
      0.0,
      0.01587301678955555,
      0.01587301678955555,
      0.0,
      0.0793650820851326,
      0.01587301678955555,
      0.2222222238779068,
      0.01587301678955555,
      0.01587301678955555,
      0.0,
      0.0317460335791111,
      0.0,
      0.0317460335791111,
      0.0317460335791111,
      0.0,
      0.01587301678955555,
      0.01587301678955555,
      0.0,
      0.01587301678955555,
      0.0,
      0.0,
      0.0,
      0.01587301678955555,
      0.0,
      0.0,
      0.0,
      0.01587301678955555,
      0.0,
      0.0317460335791111
    ]
  ],
  "region_count": 31,
  "max_intensity": 96.0,
  "mean_intensity": 1.7485498649691358,
  "artifacts": [
    {
      "kind": "raw",
      "filename": "20260315T031513-6ac187_raw.png",
      "content_type": "image/png",
      "size_bytes": 3189099,
      "sha256": "6d6aa580c777c635a52090c252e76c5da9e399aca2fdb5f9497d0c338ea0c2d9",
      "uploaded": false,
      "url": null
    },
    {
      "kind": "intensity",
      "filename": "20260315T031513-6ac187_intensity.png",
      "content_type": "image/png",
      "size_bytes": 598676,
      "sha256": "9b46a908c98fe7022acafa890a63bb66122ae9f73262d05c01cba3800ccc26d0",
      "uploaded": false,
      "url": null
    },
    {
      "kind": "mask",
      "filename": "20260315T031513-6ac187_mask.png",
      "content_type": "image/png",
      "size_bytes": 12574,
      "sha256": "5662666ff143ce30a51789fe4cd81a8b31348cc8a3e31b3a1f119c75ebf18533",
      "uploaded": false,
      "url": null
    },
    {
      "kind": "matrix",
      "filename": "20260315T031513-6ac187_matrix.npy",
      "content_type": "application/octet-stream",
      "size_bytes": 9344,
      "sha256": "72fc7dba612f6999c879b1d08fb6a3e99c1972ed8275cb347fe7a8762e7fefe5",
      "uploaded": false,
      "url": null
    }
  ]
}